couch.py
setup.py
couch.egg-info/PKG-INFO
couch.egg-info/SOURCES.txt
couch.egg-info/dependency_links.txt
couch.egg-info/entry_points.txt
couch.egg-info/top_level.txt